azurefunctions/extensions/bindings/blob/__init__.py
azurefunctions/extensions/bindings/blob/blobClient.py
azurefunctions/extensions/bindings/blob/blobClientConverter.py
azurefunctions/extensions/bindings/blob/blobSdkType.py
azurefunctions/extensions/bindings/blob/containerClient.py
azurefunctions/extensions/bindings/blob/storageStreamDownloader.py
azurefunctions/extensions/bindings/blob/utils.py
azurefunctions_extensions_bindings_blob-1.1.1.dist-info/licenses/LICENSE
samples/blob_samples_blobclient/function_app.py
samples/blob_samples_containerclient/function_app.py
samples/blob_samples_storagestreamdownloader/function_app.py
azurefunctions_extensions_bindings_blob-1.1.1.dist-info/METADATA
azurefunctions_extensions_bindings_blob-1.1.1.dist-info/WHEEL
azurefunctions_extensions_bindings_blob-1.1.1.dist-info/top_level.txt
azurefunctions_extensions_bindings_blob-1.1.1.dist-info/RECORD
